{
    "key": "group_59c25d7d2208d",
    "title": "Bar - Meta",
    "fields": [
        {
            "key": "field_59c25d836769e",
            "label": "API ID",
            "name": "api_id",
            "type": "text",
            "instructions": "",
            "required": 0,
            "conditional_logic": 0,
            "wrapper": {
                "width": "",
                "class": "",
                "id": ""
            },
            "default_value": "",
            "placeholder": "",
            "prepend": "",
            "append": "",
            "maxlength": "",
            "readonly": 0,
            "disabled": 0
        },
        {
            "key": "field_5a13ea593a4d8",
            "label": "Open Times",
            "name": "open_times",
            "type": "flexible_content",
            "instructions": "",
            "required": 0,
            "conditional_logic": 0,
            "wrapper": {
                "width": "",
                "class": "",
                "id": ""
            },
            "layouts": {
                "5a13ea7d5fa87": {
                    "key": "5a13ea7d5fa87",
                    "name": "opening_times",
                    "label": "Opening Times",
                    "display": "block",
                    "sub_fields": [
                        {
                            "key": "field_5a13ea9c3a4d9",
                            "label": "Rows",
                            "name": "rows",
                            "type": "repeater",
                            "instructions": "",
                            "required": 0,
                            "conditional_logic": 0,
                            "wrapper": {
                                "width": "",
                                "class": "",
                                "id": ""
                            },
                            "collapsed": "",
                            "min": 0,
                            "max": 0,
                            "layout": "block",
                            "button_label": "",
                            "sub_fields": [
                                {
                                    "key": "field_5a13ef693a4da",
                                    "label": "Days",
                                    "name": "days",
                                    "type": "text",
                                    "instructions": "Format MUST be short day names.",
                                    "required": 0,
                                    "conditional_logic": 0,
                                    "wrapper": {
                                        "width": "",
                                        "class": "",
                                        "id": ""
                                    },
                                    "default_value": "",
                                    "placeholder": "",
                                    "prepend": "",
                                    "append": "",
                                    "maxlength": ""
                                },
                                {
                                    "key": "field_5a13ef723a4db",
                                    "label": "Hours",
                                    "name": "hours",
                                    "type": "text",
                                    "instructions": "Format MUST be 12hour format.",
                                    "required": 0,
                                    "conditional_logic": 0,
                                    "wrapper": {
                                        "width": "",
                                        "class": "",
                                        "id": ""
                                    },
                                    "default_value": "",
                                    "placeholder": "",
                                    "prepend": "",
                                    "append": "",
                                    "maxlength": ""
                                }
                            ]
                        }
                    ],
                    "min": "",
                    "max": "1"
                },
                "5a13efab3a4dc": {
                    "key": "5a13efab3a4dc",
                    "name": "food_serving",
                    "label": "Food Serving",
                    "display": "block",
                    "sub_fields": [
                        {
                            "key": "field_5a13efab3a4dd",
                            "label": "Rows",
                            "name": "rows",
                            "type": "repeater",
                            "instructions": "",
                            "required": 0,
                            "conditional_logic": 0,
                            "wrapper": {
                                "width": "",
                                "class": "",
                                "id": ""
                            },
                            "collapsed": "",
                            "min": 0,
                            "max": 0,
                            "layout": "block",
                            "button_label": "",
                            "sub_fields": [
                                {
                                    "key": "field_5a13efab3a4de",
                                    "label": "Days",
                                    "name": "days",
                                    "type": "text",
                                    "instructions": "Format MUST be short day names.",
                                    "required": 0,
                                    "conditional_logic": 0,
                                    "wrapper": {
                                        "width": "",
                                        "class": "",
                                        "id": ""
                                    },
                                    "default_value": "",
                                    "placeholder": "",
                                    "prepend": "",
                                    "append": "",
                                    "maxlength": ""
                                },
                                {
                                    "key": "field_5a13efab3a4df",
                                    "label": "Hours",
                                    "name": "hours",
                                    "type": "text",
                                    "instructions": "Format MUST be 12hour format.",
                                    "required": 0,
                                    "conditional_logic": 0,
                                    "wrapper": {
                                        "width": "",
                                        "class": "",
                                        "id": ""
                                    },
                                    "default_value": "",
                                    "placeholder": "",
                                    "prepend": "",
                                    "append": "",
                                    "maxlength": ""
                                }
                            ]
                        }
                    ],
                    "min": "",
                    "max": "1"
                },
                "5a13efb63a4e0": {
                    "key": "5a13efb63a4e0",
                    "name": "happy_hours",
                    "label": "Happy Hours",
                    "display": "block",
                    "sub_fields": [
                        {
                            "key": "field_5a13efb63a4e1",
                            "label": "Rows",
                            "name": "rows",
                            "type": "repeater",
                            "instructions": "",
                            "required": 0,
                            "conditional_logic": 0,
                            "wrapper": {
                                "width": "",
                                "class": "",
                                "id": ""
                            },
                            "collapsed": "",
                            "min": 0,
                            "max": 0,
                            "layout": "block",
                            "button_label": "",
                            "sub_fields": [
                                {
                                    "key": "field_5a13efb63a4e2",
                                    "label": "Days",
                                    "name": "days",
                                    "type": "text",
                                    "instructions": "Format MUST be short day names.",
                                    "required": 0,
                                    "conditional_logic": 0,
                                    "wrapper": {
                                        "width": "",
                                        "class": "",
                                        "id": ""
                                    },
                                    "default_value": "",
                                    "placeholder": "",
                                    "prepend": "",
                                    "append": "",
                                    "maxlength": ""
                                },
                                {
                                    "key": "field_5a13efb63a4e3",
                                    "label": "Hours",
                                    "name": "hours",
                                    "type": "text",
                                    "instructions": "Format MUST be 12hour format.",
                                    "required": 0,
                                    "conditional_logic": 0,
                                    "wrapper": {
                                        "width": "",
                                        "class": "",
                                        "id": ""
                                    },
                                    "default_value": "",
                                    "placeholder": "",
                                    "prepend": "",
                                    "append": "",
                                    "maxlength": ""
                                }
                            ]
                        }
                    ],
                    "min": "",
                    "max": "1"
                }
            },
            "button_label": "Add Row",
            "min": "",
            "max": ""
        },
        {
            "key": "field_5a1e9d4af0c35",
            "label": "Facebook Page URL",
            "name": "facebook_page_url",
            "type": "url",
            "instructions": "",
            "required": 0,
            "conditional_logic": 0,
            "wrapper": {
                "width": "",
                "class": "",
                "id": ""
            },
            "default_value": "",
            "placeholder": ""
        },
        {
            "key": "field_5a1e9db9f0c36",
            "label": "Twitter Page URL",
            "name": "twitter_page_url",
            "type": "url",
            "instructions": "",
            "required": 0,
            "conditional_logic": 0,
            "wrapper": {
                "width": "",
                "class": "",
                "id": ""
            },
            "default_value": "",
            "placeholder": ""
        },
        {
            "key": "field_5a1e9dc8f0c37",
            "label": "Instagram Page URL",
            "name": "instagram_page_url",
            "type": "url",
            "instructions": "",
            "required": 0,
            "conditional_logic": 0,
            "wrapper": {
                "width": "",
                "class": "",
                "id": ""
            },
            "default_value": "",
            "placeholder": ""
        },
        {
            "key": "field_5a1e9e03f0c38",
            "label": "Spotify Playlist URL",
            "name": "spotify_playlist_url",
            "type": "url",
            "instructions": "",
            "required": 0,
            "conditional_logic": 0,
            "wrapper": {
                "width": "",
                "class": "",
                "id": ""
            },
            "default_value": "",
            "placeholder": ""
        },
        {
            "key": "field_5b682c8b68d84",
            "label": "Deliveroo Bar URL",
            "name": "deliveroo_bar_url",
            "type": "url",
            "instructions": "",
            "required": 0,
            "conditional_logic": 0,
            "wrapper": {
                "width": "",
                "class": "",
                "id": ""
            },
            "default_value": "https:\/\/deliveroo.co.uk\/",
            "placeholder": ""
        },
        {
            "key": "field_60817d8942693",
            "label": "Just Eat Bar URL",
            "name": "just_eat_bar_url",
            "type": "url",
            "instructions": "",
            "required": 0,
            "conditional_logic": 0,
            "wrapper": {
                "width": "",
                "class": "",
                "id": ""
            },
            "default_value": "",
            "placeholder": ""
        },
        {
            "key": "field_5a69bb41844ee",
            "label": "Bar 360 Code",
            "name": "bar_360_code",
            "type": "textarea",
            "instructions": "",
            "required": 0,
            "conditional_logic": 0,
            "wrapper": {
                "width": "",
                "class": "",
                "id": ""
            },
            "default_value": "",
            "placeholder": "",
            "maxlength": "",
            "rows": "",
            "new_lines": ""
        },
        {
            "key": "field_6275783d2cf1d",
            "label": "FIXR ID",
            "name": "fixr_id",
            "type": "text",
            "instructions": "",
            "required": 0,
            "conditional_logic": 0,
            "wrapper": {
                "width": "",
                "class": "",
                "id": ""
            },
            "default_value": "",
            "placeholder": "",
            "prepend": "",
            "append": "",
            "maxlength": ""
        }
    ],
    "location": [
        [
            {
                "param": "post_type",
                "operator": "==",
                "value": "bar"
            }
        ]
    ],
    "menu_order": 0,
    "position": "side",
    "style": "default",
    "label_placement": "top",
    "instruction_placement": "label",
    "hide_on_screen": "",
    "active": true,
    "description": "",
    "modified": 1651865684
}